simple_terminal
